crypto_com_developer_platform_client/__init__.py
crypto_com_developer_platform_client/block.py
crypto_com_developer_platform_client/client.py
crypto_com_developer_platform_client/constants.py
crypto_com_developer_platform_client/contract.py
crypto_com_developer_platform_client/cronosid.py
crypto_com_developer_platform_client/defi.py
crypto_com_developer_platform_client/event.py
crypto_com_developer_platform_client/exchange.py
crypto_com_developer_platform_client/integrations/api_interfaces.py
crypto_com_developer_platform_client/integrations/api_utils.py
crypto_com_developer_platform_client/integrations/block_api.py
crypto_com_developer_platform_client/integrations/contract_api.py
crypto_com_developer_platform_client/integrations/cronosid_api.py
crypto_com_developer_platform_client/integrations/defi_api.py
crypto_com_developer_platform_client/integrations/event_api.py
crypto_com_developer_platform_client/integrations/exchange_api.py
crypto_com_developer_platform_client/integrations/network_api.py
crypto_com_developer_platform_client/integrations/token_api.py
crypto_com_developer_platform_client/integrations/transaction_api.py
crypto_com_developer_platform_client/integrations/wallet_api.py
crypto_com_developer_platform_client/interfaces/chain_interfaces.py
crypto_com_developer_platform_client/interfaces/defi_interfaces.py
crypto_com_developer_platform_client/network.py
crypto_com_developer_platform_client/token.py
crypto_com_developer_platform_client/transaction.py
crypto_com_developer_platform_client/wallet.py
crypto_com_developer_platform_client-1.1.1.dist-info/LICENSE
crypto_com_developer_platform_client-1.1.1.dist-info/METADATA
crypto_com_developer_platform_client-1.1.1.dist-info/WHEEL
crypto_com_developer_platform_client-1.1.1.dist-info/entry_points.txt
crypto_com_developer_platform_client-1.1.1.dist-info/RECORD
