Metadata-Version: 2.3
Name: crypto-com-developer-platform-client
Version: 1.1.1
Summary: A python client to interact with @cryptocom/developer-platform-service
License: MIT
Keywords: blockchain,crypto.com,tool,SDK
Author: Ric Arcifa
Author-email: ricardo.arcifa@crypto.com
Requires-Python: >=3.8.1,<4.0.0
Classifier: License :: OSI Approved :: MIT License
Classifier: Programming Language :: Python :: 3
Classifier: Programming Language :: Python :: 3.9
Classifier: Programming Language :: Python :: 3.10
Classifier: Programming Language :: Python :: 3.11
Classifier: Programming Language :: Python :: 3.12
Classifier: Programming Language :: Python :: 3.13
Requires-Dist: requests (>=2.32.3,<3.0.0)
Project-URL: Documentation, https://github.com/crypto-com/developer-platform-client-py#readme
Project-URL: Homepage, https://github.com/crypto-com/developer-platform-client-py
Project-URL: Repository, https://github.com/crypto-com/developer-platform-client-py
